failprint-1.0.6.dist-info/METADATA
failprint-1.0.6.dist-info/WHEEL
failprint-1.0.6.dist-info/entry_points.txt
failprint-1.0.6.dist-info/licenses/LICENSE
failprint/__init__.py
failprint/__main__.py
failprint/_internal/__init__.py
failprint/_internal/capture.py
failprint/_internal/cli.py
failprint/_internal/debug.py
failprint/_internal/formats.py
failprint/_internal/lazy.py
failprint/_internal/process.py
failprint/_internal/runners.py
failprint/_internal/types.py
failprint/capture.py
failprint/cli.py
failprint/debug.py
failprint/formats.py
failprint/lazy.py
failprint/process.py
failprint/py.typed
failprint/runners.py
failprint-1.0.6.dist-info/RECORD
