Metadata-Version: 2.4
Name: failprint
Version: 1.0.6
Summary: Run a command, print its output only if it fails.
Keywords: cli,failure,output,runner
Author-Email: =?utf-8?q?Timoth=C3=A9e_Mazzucotelli?= <dev@pawamoy.fr>
License-Expression: ISC
License-File: LICENSE
Classifier: Development Status :: 4 - Beta
Classifier: Intended Audience :: Developers
Classifier: Programming Language :: Python
Classifier: Programming Language :: Python :: 3
Classifier: Programming Language :: Python :: 3 :: Only
Classifier: Programming Language :: Python :: 3.9
Classifier: Programming Language :: Python :: 3.10
Classifier: Programming Language :: Python :: 3.11
Classifier: Programming Language :: Python :: 3.12
Classifier: Programming Language :: Python :: 3.13
Classifier: Programming Language :: Python :: 3.14
Classifier: Topic :: Documentation
Classifier: Topic :: Software Development
Classifier: Topic :: Utilities
Classifier: Typing :: Typed
Project-URL: Homepage, https://pawamoy.github.io/failprint
Project-URL: Documentation, https://pawamoy.github.io/failprint
Project-URL: Changelog, https://pawamoy.github.io/failprint/changelog
Project-URL: Repository, https://github.com/pawamoy/failprint
Project-URL: Issues, https://github.com/pawamoy/failprint/issues
Project-URL: Discussions, https://github.com/pawamoy/failprint/discussions
Project-URL: Gitter, https://gitter.im/failprint/community
Project-URL: Funding, https://github.com/sponsors/pawamoy
Requires-Python: >=3.9
Requires-Dist: ansimarkup~=1.4
Requires-Dist: jinja2<4,>=2.11
Requires-Dist: ptyprocess~=0.6; sys_platform != "win32"
Requires-Dist: typing-extensions>=4.1; python_version < "3.10"
